graph_generators/__init__.py
graph_generators/graph_generators.py
graph_generators-0.1.7.dist-info/LICENSE
graph_generators-0.1.7.dist-info/METADATA
graph_generators-0.1.7.dist-info/WHEEL
graph_generators-0.1.7.dist-info/top_level.txt
graph_generators-0.1.7.dist-info/RECORD
