Metadata-Version: 2.1
Name: graph-generators
Version: 0.1.7
Summary: Python functions to compute various classes of networkx graphs
Home-page: https://github.com/postvakje/graph-generators
Author: Chai Wah Wu
Author-email: cwwuieee@gmail.com
License: LICENSE
Classifier: Programming Language :: Python :: 3
Classifier: License :: OSI Approved :: Apache Software License
Classifier: Operating System :: OS Independent
Classifier: Topic :: Scientific/Engineering :: Mathematics
Classifier: Topic :: Scientific/Engineering :: Information Analysis
Classifier: Development Status :: 4 - Beta
Classifier: Intended Audience :: Science/Research
Requires-Python: >= 3.5
License-File: LICENSE
Requires-Dist: networkx
